qtdata_setupserver_and_tool.py
qtdata_setupserver_and_tool-1.0.0.dist-info/METADATA
qtdata_setupserver_and_tool-1.0.0.dist-info/WHEEL
qtdata_setupserver_and_tool-1.0.0.dist-info/top_level.txt
qtdata_setupserver_and_tool-1.0.0.dist-info/RECORD
