Metadata-Version: 2.1
Name: qtdata-setupserver-and-tool
Version: 1.0.0
Summary: just ignore this module
Home-page: UNKNOWN
Author: cai the si
Author-email: caithesi21041997@gmail.com
License: UNKNOWN
Platform: UNKNOWN
